wml/visionml/__init__.py
wml/visionml/base.py
wml/visionml/conn.py
wml/visionml/event.py
wml/visionml/image.py
wml/visionml/image_pair.py
wml/visionml/installation.py
wml/visionml/ipv.py
wml/visionml/mutable.py
wml/visionml/muv1.py
wml/visionml/params.py
wml/visionml/segm.py
wml/visionml/slack.py
wml/visionml/sqlite.py
wml/visionml/taxcode_distribution.py
wml/visionml/version.py
wml/visionml/view.py
wml/visionml/event_munet/__init__.py
wml/visionml/event_munet/after_image.py
wml/visionml/event_munet/base.py
wml/visionml/event_munet/before_image.py
wml/visionml/event_munet/kind.py
wml/visionml/event_munet/menu.py
wml/visionml/event_munet/prediction_context.py
wml/visionml/event_munet/redundant.py
wml/visionml/event_munet/reweight.py
wml/visionml/event_munet/segm.py
wml/visionml/event_munet/target_taxcode_distribution.py
wml/visionml/event_munet/taxcode.py
wml/visionml/event_munet/taxcode_list.py
wml.visionml-2.21.202302221128.data/scripts/mutable_merge_from.py
wml.visionml-2.21.202302221128.data/scripts/mutable_sync.py
wml.visionml-2.21.202302221128.data/scripts/segm_render.py
wml.visionml-2.21.202302221128.data/scripts/segm_sync_from_muv1db.py
wml.visionml-2.21.202302221128.data/scripts/visionml_cancel_backends.py
wml.visionml-2.21.202302221128.data/scripts/visionml_play_event.py
wml.visionml-2.21.202302221128.data/scripts/visionml_recreate_views.py
wml.visionml-2.21.202302221128.data/scripts/visionml_update_segmentation_convex.py
wml.visionml-2.21.202302221128.data/scripts/visionml_update_site_details.py
wml.visionml-2.21.202302221128.data/scripts/visionml_visit_events.py
wml.visionml-2.21.202302221128.dist-info/METADATA
wml.visionml-2.21.202302221128.dist-info/WHEEL
wml.visionml-2.21.202302221128.dist-info/top_level.txt
wml.visionml-2.21.202302221128.dist-info/RECORD
